eight_bit_computer/__init__.py
eight_bit_computer/assembler.py
eight_bit_computer/assembly_summary.py
eight_bit_computer/assembly_validity.py
eight_bit_computer/bitdef.py
eight_bit_computer/cli.py
eight_bit_computer/data_structures.py
eight_bit_computer/exceptions.py
eight_bit_computer/export.py
eight_bit_computer/language_defs.py
eight_bit_computer/main.py
eight_bit_computer/number_utils.py
eight_bit_computer/operation_utils.py
eight_bit_computer/rom.py
eight_bit_computer/token_utils.py
eight_bit_computer/operations/__init__.py
eight_bit_computer/operations/add.py
eight_bit_computer/operations/copy_op.py
eight_bit_computer/operations/fetch.py
eight_bit_computer/operations/jump.py
eight_bit_computer/operations/jump_if_flag_base.py
eight_bit_computer/operations/jump_if_overflow_flag.py
eight_bit_computer/operations/load.py
eight_bit_computer/operations/operation_template.py
eight_bit_computer/operations/set_op.py
eight_bit_computer/operations/simple_alu_op_base.py
eight_bit_computer-0.0.2.dist-info/LICENSE
eight_bit_computer-0.0.2.dist-info/METADATA
eight_bit_computer-0.0.2.dist-info/WHEEL
eight_bit_computer-0.0.2.dist-info/entry_points.txt
eight_bit_computer-0.0.2.dist-info/top_level.txt
eight_bit_computer-0.0.2.dist-info/RECORD
