Metadata-Version: 2.1
Name: eight-bit-computer
Version: 0.0.2
Summary: Tools to build a physical eight bit computer.
Home-page: https://github.com/ninezerozeronine/eight-bit-computer
Author: Andy Palmer
Author-email: contactninezerozeronine@gmail.com
License: UNKNOWN
Platform: UNKNOWN
